LICENSE
MANIFEST.in
README.rst
setup.cfg
setup.py
versioneer.py
artellapipe/__init__.py
artellapipe/tools/__init__.py
artellapipe/tools/outliner/__init__.py
artellapipe/tools/outliner/__logging__.ini
artellapipe/tools/outliner/__version__.py
artellapipe/tools/outliner/_version.py
artellapipe/tools/outliner/core/__init__.py
artellapipe/tools/outliner/core/buttons.py
artellapipe/tools/outliner/core/outliner.py
artellapipe/tools/outliner/core/outlineritems.py
artellapipe/tools/outliner/core/outlinertree.py
artellapipe/tools/outliner/resources/icons/color/cameras.png
artellapipe/tools/outliner/resources/icons/color/characters.png
artellapipe/tools/outliner/resources/icons/color/fx.png
artellapipe/tools/outliner/resources/icons/color/high_poly.png
artellapipe/tools/outliner/resources/icons/color/lights.png
artellapipe/tools/outliner/resources/icons/color/low_poly.png
artellapipe/tools/outliner/resources/icons/color/override_add.png
artellapipe/tools/outliner/resources/icons/color/override_delete.png
artellapipe/tools/outliner/resources/icons/color/props.png
artellapipe/tools/outliner/resources/icons/color/shading_load.png
artellapipe/tools/outliner/resources/icons/color/shading_unload.png
artellapipe/tools/outliner/resources/icons/default/cameras.png
artellapipe/tools/outliner/resources/icons/default/characters.png
artellapipe/tools/outliner/resources/icons/default/fx.png
artellapipe/tools/outliner/resources/icons/default/high_poly.png
artellapipe/tools/outliner/resources/icons/default/lights.png
artellapipe/tools/outliner/resources/icons/default/low_poly.png
artellapipe/tools/outliner/resources/icons/default/override_add.png
artellapipe/tools/outliner/resources/icons/default/override_delete.png
artellapipe/tools/outliner/resources/icons/default/props.png
artellapipe/tools/outliner/resources/icons/default/shading_load.png
artellapipe/tools/outliner/resources/icons/default/shading_unload.png
artellapipe/tools/outliner/widgets/__init__.py
artellapipe_tools_outliner.egg-info/PKG-INFO
artellapipe_tools_outliner.egg-info/SOURCES.txt
artellapipe_tools_outliner.egg-info/dependency_links.txt
artellapipe_tools_outliner.egg-info/not-zip-safe
artellapipe_tools_outliner.egg-info/requires.txt
artellapipe_tools_outliner.egg-info/top_level.txt
