Metadata-Version: 2.1
Name: artellapipe-tools-outliner
Version: 0.0.4
Summary: Tool that manage the assets in a DCC scene
Home-page: https://github.com/ArtellaPipe/artellapipe-tools-outliner
Author: Tomas Poveda
Author-email: tpovedatd@gmail.com
License: MIT
Platform: UNKNOWN
Provides-Extra: dev
Provides-Extra: test
